__init__.py
compuestos/__init__.py
compuestos/funciones_avanzadas.py
elementales/__init__.py
elementales/funciones_basicas.py
MiPaquetePublicable-0.0.2.dist-info/LICENSE
MiPaquetePublicable-0.0.2.dist-info/METADATA
MiPaquetePublicable-0.0.2.dist-info/WHEEL
MiPaquetePublicable-0.0.2.dist-info/top_level.txt
MiPaquetePublicable-0.0.2.dist-info/RECORD
