Metadata-Version: 2.1
Name: MiPaquetePublicable
Version: 0.0.2
Summary: Descripción del paquete
Home-page: https://github.com/JorgeCardona/recursos/Publicar Paquetes PyPI
Author: Jorge Cardona
Classifier: Programming Language :: Python :: 3
Classifier: License :: OSI Approved :: MIT License
Classifier: Operating System :: OS Independent
Requires-Python: >=3.6
License-File: LICENSE
